{
  "meta": {
    "version": "2.0.0",
    "exportedAt": null,
    "description": "Techno Doggies Official Mascot Design System — Strict Apparel & Merchandise Guidelines"
  },
  "mascots": {
    "format": {
      "type": "SVG",
      "viewBox": "64x64",
      "background": "transparent",
      "style": "stroke-based"
    },
    "styling": {
      "strokeColor": "#66ff66",
      "strokeColorName": "Logo Green",
      "strokeWidth": "2-2.5px",
      "lineCap": "round",
      "lineJoin": "round"
    },
    "sizing": {
      "minimum": "24px",
      "recommended": "64px",
      "maximum": "unlimited",
      "safeArea": "10%"
    },
    "coreVariants": [
      {
        "id": "dj-dog",
        "componentName": "DJDog",
        "displayName": "DJ Dog",
        "personality": "The selector, dropping beats",
        "quote": "The kick is the heartbeat. Everything else is just atmosphere.",
        "traits": ["confident", "skilled", "authoritative"],
        "approvedForApparel": true
      },
      {
        "id": "ninja-dog",
        "componentName": "NinjaDog",
        "displayName": "Ninja Dog",
        "personality": "Silent warrior of the night",
        "quote": "Move in silence. Let the bass speak.",
        "traits": ["mysterious", "stealthy", "legendary"],
        "approvedForApparel": true
      },
      {
        "id": "space-dog",
        "componentName": "SpaceDog",
        "displayName": "Space Dog",
        "personality": "Cosmic explorer of sound",
        "quote": "Beyond the stars, there's only rhythm.",
        "traits": ["dreamy", "transcendent", "otherworldly"],
        "approvedForApparel": true
      },
      {
        "id": "grumpy-dog",
        "componentName": "GrumpyDog",
        "displayName": "Grumpy Dog",
        "personality": "The cynical veteran",
        "quote": "Back in my day, we had REAL 303s.",
        "traits": ["sarcastic", "experienced", "secretly passionate"],
        "approvedForApparel": true
      },
      {
        "id": "happy-dog",
        "componentName": "HappyDog",
        "displayName": "Happy Dog",
        "personality": "Pure positive energy",
        "quote": "Every beat is a blessing!",
        "traits": ["enthusiastic", "uplifting", "contagious"],
        "approvedForApparel": true
      },
      {
        "id": "techno-dog",
        "componentName": "TechnoDog",
        "displayName": "Techno Dog",
        "personality": "Glitched out & digital",
        "quote": "01001011 01001001 01000011 01001011",
        "traits": ["technical", "glitchy", "futuristic"],
        "approvedForApparel": true
      },
      {
        "id": "dancing-dog",
        "componentName": "DancingDog",
        "displayName": "Dancing Dog",
        "personality": "Always moving",
        "quote": "Can't stop, won't stop. The floor is life.",
        "traits": ["energetic", "rhythmic", "unstoppable"],
        "approvedForApparel": true
      },
      {
        "id": "acid-dog",
        "componentName": "AcidDog",
        "displayName": "Acid Dog",
        "personality": "Deep repetitive vibes",
        "quote": "The 303 knows all. Surrender to the squelch.",
        "traits": ["trippy", "deep", "mesmerizing"],
        "approvedForApparel": true
      }
    ]
  },
  "colors": {
    "primary": {
      "name": "Logo Green",
      "hsl": "100 100% 60%",
      "hex": "#66ff66",
      "rgb": "102, 255, 102",
      "usage": "Mascot stroke color - THE ONLY approved accent color"
    },
    "secondary": {
      "name": "White",
      "hex": "#ffffff",
      "usage": "Alternative stroke color for light backgrounds only"
    },
    "printCMYK": {
      "c": 60,
      "m": 0,
      "y": 60,
      "k": 0
    }
  },
  "merchandise": {
    "zeroTolerancePolicy": {
      "description": "ALL merchandise must strictly follow these guidelines. Non-compliant designs are PROHIBITED.",
      "rules": [
        "ONLY use the 8 core Techno Doggy variants listed in coreVariants",
        "ONLY use Logo Green (#66ff66) or White (#ffffff) for mascot strokes",
        "NEVER use AI-generated or modified versions of the doggies",
        "NEVER change stroke width, style, or proportions",
        "NEVER add backgrounds, shadows, or effects to the mascots",
        "ALWAYS use dark fabric (black preferred) for Logo Green designs",
        "ALWAYS maintain transparent backgrounds in print files",
        "ALWAYS use official SVG exports from DogPack.tsx"
      ]
    },
    "approvedProductTypes": [
      {
        "type": "Hoodie",
        "placement": "chest center",
        "printSize": "120mm",
        "fabricColors": ["black"],
        "strokeColors": ["#66ff66", "#ffffff"]
      },
      {
        "type": "T-Shirt",
        "placement": "chest center",
        "printSize": "100mm",
        "fabricColors": ["black"],
        "strokeColors": ["#66ff66", "#ffffff"]
      },
      {
        "type": "Cap",
        "placement": "front center",
        "printSize": "40mm",
        "fabricColors": ["black"],
        "strokeColors": ["#66ff66", "#ffffff"]
      },
      {
        "type": "Tote",
        "placement": "front center",
        "printSize": "150mm",
        "fabricColors": ["black", "natural cotton"],
        "strokeColors": ["#66ff66", "#ffffff"]
      },
      {
        "type": "Bandana",
        "placement": "center tile",
        "printSize": "80mm",
        "fabricColors": ["black"],
        "strokeColors": ["#66ff66"]
      }
    ],
    "collectionNaming": {
      "greenLine": {
        "prefix": "Green Line",
        "description": "Black fabric with Logo Green (#66ff66) stroke mascot",
        "example": "Green Line Hoodie – DJ Dog"
      },
      "whiteLine": {
        "prefix": "White Line",
        "description": "Black fabric with White (#ffffff) stroke mascot",
        "example": "White Line Tee – Space Dog"
      }
    },
    "printRequirements": {
      "resolution": "300 DPI minimum",
      "colorMode": "CMYK for print",
      "format": "PNG with transparency",
      "clearSpace": "10% of mascot size minimum"
    }
  },
  "usage": {
    "web": {
      "darkBackground": {
        "description": "Primary usage on dark backgrounds",
        "recommended": true
      },
      "cards": {
        "description": "Subtle container with primary border hint"
      },
      "sizes": {
        "icon": "24-32px",
        "card": "48-64px",
        "hero": "128-256px"
      }
    },
    "mobile": {
      "appIcon": {
        "placement": "centered",
        "containerRatio": "60%"
      },
      "notification": {
        "size": "32px"
      },
      "loading": {
        "animated": true
      }
    },
    "social": {
      "sticker": {
        "size": "512x512px",
        "format": "PNG",
        "maxFileSize": "100KB",
        "background": "transparent"
      },
      "hashtagFormat": "#[variant]doggy",
      "messageTemplate": {
        "short": "I'm the [Variant] — [Quote]. #[variant]doggy",
        "full": "I'm the [Variant] — [personality]. '[Quote]' Join the pack: techno.dog/doggies #[variant]doggy"
      }
    }
  },
  "language": {
    "voicePrinciples": [
      "Irreverent & Witty — Self-aware humor",
      "Authentic & Underground — Real culture references",
      "Casual Slang — Modern informal language",
      "Knowledgeable & Nerdy — Deep subject matter expertise",
      "Inclusive & Warm — Welcoming to newcomers"
    ],
    "toneGuidelines": {
      "avoid": [
        "Corporate speak",
        "Generic enthusiasm",
        "AI-sounding phrases",
        "Overused emojis"
      ],
      "use": [
        "Specific gear references (303, 909, Minimoog)",
        "Scene terminology (selector, crate digging, the floor)",
        "Time/place anchors (4AM, warehouse, dark room)"
      ]
    },
    "approvedSlang": {
      "no cap": "for real, honestly",
      "lowkey": "subtly, quietly",
      "it's giving": "it has the vibe of",
      "ngl": "not gonna lie",
      "fr fr": "for real for real",
      "bussin": "extremely good",
      "unhinged": "wild, chaotic energy",
      "understood the assignment": "nailed it perfectly"
    }
  },
  "guidelines": {
    "do": [
      "Use official SVG components from DogPack.tsx ONLY",
      "Maintain transparent backgrounds",
      "Scale proportionally",
      "Use on dark backgrounds for best visibility",
      "Include hashtag when sharing",
      "Credit techno.dog on external uses",
      "Follow exact placement and sizing specs for merchandise"
    ],
    "dont": [
      "Change the Logo Green color",
      "Add backgrounds or effects",
      "Distort or stretch the mascots",
      "Use on busy or colorful backgrounds",
      "Combine with generic icons or emojis",
      "Use for commercial purposes without permission",
      "Create custom or AI-generated variations",
      "Use non-core variants for merchandise"
    ]
  }
}
